LICENSE
MANIFEST.in
README.rst
requirements.txt
setup.py
tox.ini
os3/__init__.py
os3/sc.py
os3.egg-info/PKG-INFO
os3.egg-info/SOURCES.txt
os3.egg-info/dependency_links.txt
os3.egg-info/not-zip-safe
os3.egg-info/pbr.json
os3.egg-info/requires.txt
os3.egg-info/top_level.txt
os3/core/__init__.py
os3/core/comparators.py
os3/core/item.py
os3/core/list.py
os3/data/__init__.py
os3/data/item.py
os3/data/list.py
os3/data/tree.py
os3/fs/__init__.py
os3/fs/directory.py
os3/fs/entry.py
os3/fs/file.py
os3/fs/shortcuts.py
os3/fs/utils.py
os3/ps/__init__.py
os3/ps/process.py
os3/ps/processes.py
os3/tests/__init__.py
os3/tests/base.py
os3/tests/core/__init__.py
os3/tests/core/tests.py
os3/tests/data/__init__.py
os3/tests/data/tests.py
os3/utils/__init__.py
os3/utils/console.py
os3/utils/decorators.py
os3/utils/iter.py
os3/utils/nodes.py