Metadata-Version: 1.1
Name: os3
Version: 0.1.1
Summary: Package description
